django_data_sdk/__init__.py
django_data_sdk/admin.py
django_data_sdk/apps.py
django_data_sdk/collector.py
django_data_sdk/middleware.py
django_data_sdk/models.py
django_data_sdk/tasks.py
django_data_sdk/views.py
django_data_sdk/conf/__init__.py
django_data_sdk/conf/settings.py
django_data_sdk/migrations/__init__.py
django_data_sdk/sink/__init__.py
django_data_sdk/sink/base.py
django_data_sdk/sink/impl.py
django_data_sdk/sink/mode.py
django_data_sdk/sink/utils.py
django_data_sdk/sink/backends/__init__.py
django_data_sdk/sink/backends/backend_django_data.py
django_data_sdk/sink/backends/backend_dummy.py
django_data_sdk/sink/backends/backend_kafka.py
django_data_sdk/sink/backends/base.py
tests/__init__.py
tests/test_collector.py
tests/test_settings.py
tests/test_sink.py
django_data_sdk-0.0.22.dist-info/METADATA
django_data_sdk-0.0.22.dist-info/WHEEL
django_data_sdk-0.0.22.dist-info/top_level.txt
django_data_sdk-0.0.22.dist-info/RECORD
