Metadata-Version: 2.1
Name: django-data-sdk
Version: 0.0.22
Author: Felix
Author-email: fei@eano.com
License: MIT
Classifier: Development Status :: 5 - Production/Stable
Classifier: Framework :: Django :: 2
Classifier: Framework :: Django :: 3
Classifier: Framework :: Django :: 4
Classifier: License :: OSI Approved :: Apache Software License
Classifier: Operating System :: OS Independent
Classifier: Programming Language :: Python :: 3 :: Only
Requires-Python: >=3.8
Requires-Dist: django (>=2.2.28)
Requires-Dist: celery (>=4.4.7)
Requires-Dist: kafka-python (>=2.0.2)
